{
  "parent": "pumpkin_carving:item/pumpkin",
  "elements": [
    {
      "from": [
        4,
        5,
        0
      ],
      "to": [
        5,
        6,
        1
      ],
      "faces": {
        "north": {
          "uv": [
            11,
            10,
            12,
            11
          ],
          "texture": "#0"
        },
        "east": {
          "uv": [
            15,
            10,
            16,
            11
          ],
          "texture": "#4"
        },
        "south": {
          "uv": [
            4,
            10,
            5,
            11
          ],
          "texture": "#4"
        },
        "west": {
          "uv": [
            0,
            10,
            1,
            11
          ],
          "texture": "#4"
        },
        "up": {
          "uv": [
            4,
            0,
            5,
            1
          ],
          "texture": "#4"
        },
        "down": {
          "uv": [
            4,
            15,
            5,
            16
          ],
          "texture": "#4"
        }
      }
    }
  ]
}
