{
  "parent": "pumpkin_carving:item/pumpkin",
  "elements": [
    {
      "from": [
        9,
        15,
        5
      ],
      "to": [
        10,
        16,
        6
      ],
      "faces": {
        "north": {
          "uv": [
            6,
            0,
            7,
            1
          ],
          "texture": "#4"
        },
        "east": {
          "uv": [
            10,
            0,
            11,
            1
          ],
          "texture": "#4"
        },
        "south": {
          "uv": [
            9,
            0,
            10,
            1
          ],
          "texture": "#4"
        },
        "west": {
          "uv": [
            5,
            0,
            6,
            1
          ],
          "texture": "#4"
        },
        "up": {
          "uv": [
            9,
            5,
            10,
            6
          ],
          "texture": "#1"
        },
        "down": {
          "uv": [
            9,
            10,
            10,
            11
          ],
          "texture": "#4"
        }
      }
    }
  ]
}
